odoo/addons/add_external_id/README.rst
odoo/addons/add_external_id/__init__.py
odoo/addons/add_external_id/__manifest__.py
odoo/addons/add_external_id/models/__init__.py
odoo/addons/add_external_id/models/account_account.py
odoo/addons/add_external_id/static/description/icon.png
odoo11_addon_add_external_id-11.0.1.0.0.99.dev1.dist-info/METADATA
odoo11_addon_add_external_id-11.0.1.0.0.99.dev1.dist-info/WHEEL
odoo11_addon_add_external_id-11.0.1.0.0.99.dev1.dist-info/top_level.txt
odoo11_addon_add_external_id-11.0.1.0.0.99.dev1.dist-info/RECORD
